xplant/__init__.py
xplant/_attr_reg.py
xplant/_six.py
xplant/_xml_attributes.py
xplant/engine.py
xplant/html.py
xplant/svg.py
xplant/xml.py
xplant/yaml.py
xplant-1.0.0.dist-info/LICENSE
xplant-1.0.0.dist-info/METADATA
xplant-1.0.0.dist-info/WHEEL
xplant-1.0.0.dist-info/top_level.txt
xplant-1.0.0.dist-info/RECORD
